LICENSE.txt
README.md
setup.cfg
setup.py
isea_plots/__init__.py
isea_plots/isea_plots.py
isea_plots.egg-info/PKG-INFO
isea_plots.egg-info/SOURCES.txt
isea_plots.egg-info/dependency_links.txt
isea_plots.egg-info/requires.txt
isea_plots.egg-info/top_level.txt