Metadata-Version: 2.1
Name: isea-plots
Version: 0.2
Summary: A package for creating plots according to ISEA style
Home-page: https://github.com/NajetNsir/isea_plots
Download-URL: https://github.com/NajetNsir/isea_plots/archive/refs/tags/v_02.tar.gz
Author: Najet Nsir
Author-email: najet.nsir@isea.rwth-aachen.de
License: MIT
License-File: LICENSE.txt
